MANIFEST.in
README.md
amazonify.py
requirements.txt
setup.py
tests.py
amazonify.egg-info/PKG-INFO
amazonify.egg-info/SOURCES.txt
amazonify.egg-info/dependency_links.txt
amazonify.egg-info/not-zip-safe
amazonify.egg-info/top_level.txt
assets/amazonify.jpg