Metadata-Version: 1.0
Name: amazonify
Version: 0.1
Summary: The simplest way to build Amazon Affiliate links, in Python.
Home-page: https://github.com/rdegges/amazonify
Author: Randall Degges
Author-email: rdegges@gmail.com
License: UNLICENSE
Keywords: amazon affiliate web
Platform: UNKNOWN
